dtrader_level2_client-1.0.1.dist-info/licenses/LICENSE
examples/basic_example.py
examples/online_package_demo.py
examples/quick_start.py
dtrader_level2_client-1.0.1.dist-info/METADATA
dtrader_level2_client-1.0.1.dist-info/WHEEL
dtrader_level2_client-1.0.1.dist-info/top_level.txt
dtrader_level2_client-1.0.1.dist-info/RECORD
